Metadata-Version: 1.1
Name: uspspy
Version: 0.0.2
Summary: Validate addresses with the USPS API.
Home-page: https://poplars.dev
Author: Chris Binckly, Poplar Development
Author-email: chris@poplars.dev
License: UNKNOWN
Keywords: USPS Address Validation API XML
Platform: UNKNOWN
Classifier: Development Status :: 4 - Beta
Classifier: Intended Audience :: Developers
Classifier: Topic :: Software Development :: Build Tools
Classifier: Environment :: Win32 (MS Windows)
Classifier: Operating System :: Microsoft :: Windows
Classifier: Programming Language :: Python :: 3.4
Classifier: License :: OSI Approved :: GNU General Public License v3 (GPLv3)
